{
  "version": 1,
  "revision": 19,
  "id": "local-portal-access",
  "profiles": [
    {
      "version": 1,
      "revision": 19,
      "id": "local-operations-login",
      "tenantId": "local",
      "portalId": "operations",
      "route": "/",
      "domains": ["127.0.0.1", "localhost"],
      "platformProfile": {
        "id": "portal-default",
        "revision": 20,
        "digest": "186f17bf13d455739370f7522526f8928874144394224f764d69a473b24444ae"
      },
      "accessTemplate": "access",
      "localization": {
        "defaultLocale": "zh-CN",
        "supportedLocales": ["zh-CN", "en-US"]
      },
      "authentication": {
        "allowedMethods": ["password", "one-time-code"],
        "defaultMethod": "password",
        "reuseIdentifier": true
      },
      "branding": {
        "productName": {
          "zh-CN": "VastPlan 平台管理中心",
          "en-US": "VastPlan Platform Center"
        },
        "supportPath": "/support",
        "privacyPath": "/privacy"
      }
    }
  ]
}
