{
  "id":"cn.vastplan.foundation.security.authentication.provider.database",
  "name":"VastPlan Database User Authentication Provider",
  "description":"通过通用 Database Runtime 查询企业用户并验证 Argon2id 密码",
  "version":"0.1.0","publisher":"vastplan","license":"Apache-2.0","licenseFile":"LICENSE","noticeFile":"NOTICE",
  "engines":{"backend":"^0.1"},
  "contextAccess":{"required":["scope.tenant","caller","grant.credentials"],"optional":["trace","request.deadline","propagation.callPath"]},
  "runtime":{"instancePolicy":"leader","stateModel":"leader-owned","visibility":"cluster","routing":"leader","routingDomain":"security","requires":[{"capability":"foundation.data.relational.runtime","scope":"remote","kind":"strong","ready":"readiness","failurePolicy":"degrade","logicalService":"foundation.database.runtime","routingDomain":"data"}]},
  "execution":{"backend":{"driver":"native","minimumIsolation":"trusted-process"}},
  "configuration":{"scope":"service","applyMode":"hot","schema":{"type":"object","additionalProperties":false,"required":["profiles"],"properties":{"profiles":{"type":"object","minProperties":1,"maxProperties":64,"additionalProperties":{"type":"object","additionalProperties":false,"required":["connection","lookupSql","subjectColumn","passwordHashColumn","disabledColumn","issuer"],"properties":{"connection":{"type":"object","additionalProperties":false,"required":["resourceId","revision"],"properties":{"resourceId":{"type":"string","minLength":1,"maxLength":160},"revision":{"type":"integer","minimum":1}}},"lookupSql":{"type":"string","minLength":1,"maxLength":4096},"subjectColumn":{"type":"string","minLength":1,"maxLength":160},"passwordHashColumn":{"type":"string","minLength":1,"maxLength":160},"disabledColumn":{"type":"string","minLength":1,"maxLength":160},"issuer":{"type":"string","minLength":1,"maxLength":512}}}}}}},
  "activation":["onStartup","onPortalStartup"],"entry":{"backend":"backend/database-authentication"},
  "contributes":{"backend":{"authenticationProviders":[{"id":"database-user","service_role":"backend","title":"数据库用户认证 Provider","protocol":"authentication.method.v1","purposes":["portal-login"],"methods":[{"id":"database-password","kind":"password","interaction":"form"}],"subjectNamespace":"enterprise.identity.database","requiredCapabilities":["foundation.data.relational.runtime"]}]}}
}
